nurses_2/__init__.py
nurses_2/app.py
nurses_2/clamp.py
nurses_2/data_structures.py
nurses_2/easings.py
nurses_2/fonts.py
nurses_2/spinners.py
nurses_2/colors/__init__.py
nurses_2/colors/color_data_structures.py
nurses_2/colors/colors.py
nurses_2/colors/gradients.py
nurses_2/io/__init__.py
nurses_2/io/win32_types.py
nurses_2/io/input/__init__.py
nurses_2/io/input/events.py
nurses_2/io/input/keys.py
nurses_2/io/input/vt100/__init__.py
nurses_2/io/input/vt100/ansi_escapes.py
nurses_2/io/input/vt100/console_input.py
nurses_2/io/input/vt100/mouse_bindings.py
nurses_2/io/input/vt100/vt100_input.py
nurses_2/io/input/win32/__init__.py
nurses_2/io/input/win32/console_input.py
nurses_2/io/input/win32/key_codes.py
nurses_2/io/input/win32/win32_input.py
nurses_2/io/output/__init__.py
nurses_2/io/output/vt100.py
nurses_2/io/output/windows10.py
nurses_2/widgets/__init__.py
nurses_2/widgets/_binary_to_char.py
nurses_2/widgets/_root.py
nurses_2/widgets/_smooth_bars.py
nurses_2/widgets/animation.py
nurses_2/widgets/bar_chart.py
nurses_2/widgets/box_image.py
nurses_2/widgets/braille_image.py
nurses_2/widgets/braille_video_player.py
nurses_2/widgets/button.py
nurses_2/widgets/color_picker.py
nurses_2/widgets/data_table.py
nurses_2/widgets/digital_display.py
nurses_2/widgets/file_chooser.py
nurses_2/widgets/flat_toggle.py
nurses_2/widgets/graphic_field.py
nurses_2/widgets/graphic_widget.py
nurses_2/widgets/graphic_widget_data_structures.py
nurses_2/widgets/grid_layout.py
nurses_2/widgets/image.py
nurses_2/widgets/line_plot.py
nurses_2/widgets/menu.py
nurses_2/widgets/parallax.py
nurses_2/widgets/progress_bar.py
nurses_2/widgets/raycaster.py
nurses_2/widgets/scroll_view.py
nurses_2/widgets/shadow_caster.py
nurses_2/widgets/slider.py
nurses_2/widgets/sparkline.py
nurses_2/widgets/split_layout.py
nurses_2/widgets/tabbed_widget.py
nurses_2/widgets/text_animation.py
nurses_2/widgets/text_field.py
nurses_2/widgets/text_pad.py
nurses_2/widgets/text_panel.py
nurses_2/widgets/text_widget.py
nurses_2-0.25.0.dist-info/LICENSE
nurses_2-0.25.0.dist-info/METADATA
nurses_2-0.25.0.dist-info/WHEEL
nurses_2-0.25.0.dist-info/top_level.txt
nurses_2-0.25.0.dist-info/RECORD
