Metadata-Version: 2.1
Name: nurses-2
Version: 0.25.0
Summary: A widgetful and async-centric library for terminal graphics.
Author-email: salt-die <salt-die@protonmail.com>
License: MIT
Project-URL: repository, https://github.com/salt-die/nurses_2
Project-URL: documentation, https://salt-die.github.io/nurses_2/index.html
Classifier: Programming Language :: Python :: 3
Classifier: License :: OSI Approved :: MIT License
Classifier: Operating System :: OS Independent
Requires-Python: >=3.10
License-File: LICENSE
Requires-Dist: numpy >=1.21.2
Requires-Dist: opencv-python >=4.5.4.58
Requires-Dist: wcwidth >=0.2.5
